bitcom/__init__.py
bitcom/client/__init__.py
bitcom/client/account_client.py
bitcom/client/block_trade_client.py
bitcom/client/market_client.py
bitcom/client/order_client.py
bitcom/client/subscribe_client.py
bitcom/client/system_client.py
bitcom/client/ws_auth_client.py
bitcom/connection/__init__.py
bitcom/connection/restapi_sync_client.py
bitcom/connection/impl/__init__.py
bitcom/connection/impl/restapi_invoker.py
bitcom/connection/impl/restapi_request.py
bitcom/constant/__init__.py
bitcom/constant/config.py
bitcom/constant/system.py
bitcom/exception/__init__.py
bitcom/exception/bitcom_api_exception.py
bitcom/service/__init__.py
bitcom/service/account/__init__.py
bitcom/service/account/config_cod.py
bitcom/service/account/get_accounts.py
bitcom/service/account/get_cod_config.py
bitcom/service/account/get_mmp_state.py
bitcom/service/account/get_user_deliveries.py
bitcom/service/account/get_user_positions.py
bitcom/service/account/get_user_settlements.py
bitcom/service/account/get_user_transaction_logs.py
bitcom/service/account/reset_mmp_state.py
bitcom/service/account/update_mmp_config.py
bitcom/service/block_trade/__init__.py
bitcom/service/block_trade/place_block_trade_order.py
bitcom/service/block_trade/query_block_trades.py
bitcom/service/block_trade/query_block_trades_by_platform.py
bitcom/service/market/__init__.py
bitcom/service/market/get_currencies.py
bitcom/service/market/get_delivery_info.py
bitcom/service/market/get_funding_rate.py
bitcom/service/market/get_funding_rate_history.py
bitcom/service/market/get_index.py
bitcom/service/market/get_instruments.py
bitcom/service/market/get_klines.py
bitcom/service/market/get_market_summary.py
bitcom/service/market/get_market_trades.py
bitcom/service/market/get_orderbooks.py
bitcom/service/market/get_tickers.py
bitcom/service/market/get_total_volume.py
bitcom/service/order/__init__.py
bitcom/service/order/amend_batch_orders.py
bitcom/service/order/amend_orders.py
bitcom/service/order/cancel_orders.py
bitcom-0.0.4.dist-info/LICENCE
bitcom-0.0.4.dist-info/METADATA
bitcom-0.0.4.dist-info/WHEEL
bitcom-0.0.4.dist-info/top_level.txt
bitcom-0.0.4.dist-info/RECORD
